{
  "title": "Presentazione",
  "scene": "scene.png",
  "dialogue": [
    { "speaker": "stella", "text": "Ciao e benvenut* in casa mia... mi devo abituare a questa cosa, ahah!" },
    { "speaker": "stella", "text": "Insomma, se non lo sai già: per un mese potrai seguirmi nella mia quotidianità." },
    { "speaker": "stella", "text": "Se non mi conosci... il mio nome è Stella, ho 20 anni. Dicono che sono una persona socievole e gentile." },
    { "speaker": "stella", "text": "Mi piace passare il tempo con i miei amici, il mio ragazzo e la mia famiglia, quindi sicuramente li conoscerai!" },
    { "speaker": "stella", "text": "Ti invito a seguirmi su Insta, mi trovi come @stelladaily.official: lì troverai tantissimi contenuti extra!" },
    { "speaker": "stella", "text": "Spero ci divertiremo!" }
  ],
  "objects": []
}
